InnerCensor/__init__.py
InnerCensor/commands.py
InnerCensor/main.py
InnerCensor/bin/run_censor.py
incen-0.0.1.data/scripts/run_censor.py
incen-0.0.1.dist-info/LICENSE
incen-0.0.1.dist-info/METADATA
incen-0.0.1.dist-info/WHEEL
incen-0.0.1.dist-info/entry_points.txt
incen-0.0.1.dist-info/top_level.txt
incen-0.0.1.dist-info/RECORD
