Metadata-Version: 2.1
Name: incen
Version: 0.0.1
Summary: A Telegram client for convenient compromising cleansing
Home-page: https://github.com/RedSnail/incen
Author: Oleg Demianchenko
Author-email: oleg.demianchenko@gmail.com
License: MIT
Platform: OS Independent
Requires-Python: >=3.4
License-File: LICENSE
Requires-Dist: pip (==21.3.1)
Requires-Dist: pyaes (==1.6.1)
Requires-Dist: pyasn1 (==0.4.8)
Requires-Dist: rsa (==4.8)
Requires-Dist: setuptools (==60.2.0)
Requires-Dist: Telethon (==1.24.0)
Requires-Dist: termcolor (==1.1.0)
Requires-Dist: wheel (==0.37.1)
Requires-Dist: pytz (==2022.1)
